res/__init__.py
res/constants.py
res/help.html
res/license.html
res/mainapp.py
res/tools.py
res/ux_logo_white_16.png
res/ux_logo_white_32.png
res/ux_logo_white_64.png
res/views.py
tests/__init__.py
tests/test_time.py
unix_time_converter-1.0.16.dist-info/licenses/LICENSE.md
unix_time_converter-1.0.16.dist-info/METADATA
unix_time_converter-1.0.16.dist-info/WHEEL
unix_time_converter-1.0.16.dist-info/entry_points.txt
unix_time_converter-1.0.16.dist-info/top_level.txt
unix_time_converter-1.0.16.dist-info/RECORD
